pyautomate/__init__.py
pyautomate/fs.py
pyautomate/pdf.py
pyautomate/office/__init__.py
pyautomate/web/__init__.py
pyautomate/web/__main__.py
pyautomate/web/crawler.py
pyautomate/web/html.py
pyautomate-0.1.3.dist-info/DESCRIPTION.rst
pyautomate-0.1.3.dist-info/METADATA
pyautomate-0.1.3.dist-info/RECORD
pyautomate-0.1.3.dist-info/WHEEL
pyautomate-0.1.3.dist-info/metadata.json
pyautomate-0.1.3.dist-info/top_level.txt
